{
    "ID": 1,
    "Subscription_ID": 0,
    "Created": "2015-07-25 14:38:58",
    "Name": "DB Schenker",
    "Logo_URL": "http://whereatcloud.com/images/logo.png",
    "Routes": [
        {
            "ID": 83,
            "BLE_Tracker_ID": 4,
            "Start": "2015-10-25 20:34:29",
            "End": null,
            "Orders" : [
                {
                    "ID"  : 10011000,
                    "Customer_ID" : 262900,
                    "Created" : "2015-11-19 10:56:23",
                    "Cases" : [
                        "ID" : 123,
                        "BLE_Tag_ID",
                    ]
                }

            ]
        },
        {
            "ID": 84,
            "BLE_Tracker_ID": 4,
            "Start": "2015-10-25 20:34:43",
            "End": null
        },
        {
            "ID": 85,
            "BLE_Tracker_ID": 4,
            "Start": "2015-10-25 20:34:43",
            "End": null
        },
        {
            "ID": 86,
            "BLE_Tracker_ID": 4,
            "Start": "2015-10-25 20:36:06",
            "End": null
        },
        {
            "ID": 87,
            "BLE_Tracker_ID": 4,
            "Start": "2015-10-25 20:36:07",
            "End": null
        },
        {
            "ID": 88,
            "BLE_Tracker_ID": 4,
            "Start": "2015-10-25 20:36:08",
            "End": null
        },
        {
            "ID": 89,
            "BLE_Tracker_ID": 4,
            "Start": "2015-10-25 20:36:40",
            "End": null
        },
        {
            "ID": 90,
            "BLE_Tracker_ID": 4,
            "Start": "2015-10-25 20:36:48",
            "End": null
        },
        {
            "ID": 91,
            "BLE_Tracker_ID": 4,
            "Start": "2015-10-25 20:37:51",
            "End": null
        },
        {
            "ID": 92,
            "BLE_Tracker_ID": 4,
            "Start": "2015-10-25 20:38:30",
            "End": null
        },
        {
            "ID": 93,
            "BLE_Tracker_ID": 4,
            "Start": "2015-10-25 20:40:24",
            "End": null
        },
        {
            "ID": 94,
            "BLE_Tracker_ID": 4,
            "Start": "2015-10-25 20:52:16",
            "End": null
        },
        {
            "ID": 95,
            "BLE_Tracker_ID": 4,
            "Start": "2015-10-25 20:52:32",
            "End": null
        },
        {
            "ID": 96,
            "BLE_Tracker_ID": 4,
            "Start": "2015-10-25 20:53:44",
            "End": null
        },
        {
            "ID": 97,
            "BLE_Tracker_ID": 4,
            "Start": "2015-10-25 20:54:47",
            "End": null
        },
        {
            "ID": 98,
            "BLE_Tracker_ID": 4,
            "Start": "2015-10-25 21:04:15",
            "End": null
        },
        {
            "ID": 80,
            "BLE_Tracker_ID": 5,
            "Start": "2015-08-15 18:27:19",
            "End": "2015-01-01 02:03:36"
        },
        {
            "ID": 81,
            "BLE_Tracker_ID": 5,
            "Start": "2015-08-15 18:31:51",
            "End": null
        },
        {
            "ID": 82,
            "BLE_Tracker_ID": 5,
            "Start": "2015-08-15 18:40:23",
            "End": null
        }
    ],
    "BLE_Trackers": [
        {
            "ID": 4,
            "Device_ID": "testDevice",
            "Install_ID": "testInstall",
            "Company_ID": 1,
            "Created": "2015-07-28 17:32:19"
        },
        {
            "ID": 5,
            "Device_ID": "LGD855c16e0b3",
            "Install_ID": "1f1d7644-6973-49d3-afa9-fd434855457f",
            "Company_ID": 1,
            "Created": "2015-07-28 17:32:43"
        },
        {
            "ID": 6,
            "Device_ID": "testDevice",
            "Install_ID": "testInstall2",
            "Company_ID": 1,
            "Created": "2015-07-29 18:16:37"
        }
    ],
    "BLE_Tags": [
        {
            "ID": 1,
            "Company_ID": 1,
            "Last_Updated": "2015-07-27 11:50:47",
            "Name": "whereAt T",
            "Mac_Address": "ED779659D1F1"
        },
        {
            "ID": 2,
            "Company_ID": 1,
            "Last_Updated": "2015-07-27 11:53:59",
            "Name": "whereAt T",
            "Mac_Address": "C5E51459A0A7"
        }
    ]
}